LICENSE
LICENSE.third-party
MANIFEST.in
README.md
setup.py
django_attach/__init__.py
django_attach/admin.py
django_attach/apps.py
django_attach/forms.py
django_attach/models.py
django_attach/urls.py
django_attach.egg-info/PKG-INFO
django_attach.egg-info/SOURCES.txt
django_attach.egg-info/dependency_links.txt
django_attach.egg-info/top_level.txt
django_attach/static/django_attach/css/attachment_inline.css
django_attach/static/django_attach/img/icon-revert.svg
django_attach/static/django_attach/js/attachment_inline.js
django_attach/static/django_attach/js/d3.v3.min.js
django_attach/static/django_attach/js/queue.v1.min.js
django_attach/templates/django_attach/attachment_inline.html
example_project/README.md
example_project/manage.py
example_project/app/__init__.py
example_project/app/admin.py
example_project/app/apps.py
example_project/app/models.py
example_project/app/tests.py
example_project/app/urls.py
example_project/app/views.py
example_project/app/migrations/__init__.py
example_project/app/static/app/base.css
example_project/app/templates/app/article_detail.html
example_project/app/templates/app/article_list.html
example_project/app/templates/app/base.html
example_project/app/templatetags/__init__.py
example_project/app/templatetags/baseurl.py
example_project/app/templatetags/markup.py
example_project/db/django-attach.sqlite
example_project/example_project/__init__.py
example_project/example_project/settings.py
example_project/example_project/urls.py
example_project/example_project/wsgi.py
example_project/media/attachment/app/article/1/django.gif
example_project/media/attachment/app/article/1/more.txt
example_project/media/attachment/app/article/2/django.gif
screenshots/1.png
screenshots/2.png
screenshots/3.png