Metadata-Version: 1.1
Name: django-attach
Version: 1.3.0
Summary: Django admin plugin for attaching files to model instances with multiple file selection support
Home-page: https://github.com/peterkuma/django-attach/
Author: Peter Kuma
Author-email: peter@peterkuma.net
License: BSD License
Platform: UNKNOWN
Classifier: Environment :: Web Environment
Classifier: Framework :: Django
Classifier: Intended Audience :: Developers
Classifier: License :: OSI Approved :: BSD License
Classifier: Operating System :: OS Independent
Classifier: Programming Language :: Python
Classifier: Programming Language :: Python :: 2
Classifier: Programming Language :: Python :: 2.7
Classifier: Programming Language :: Python :: 3
Classifier: Topic :: Internet :: WWW/HTTP
Classifier: Topic :: Internet :: WWW/HTTP :: Dynamic Content
